economypackage/__init__.py
economypackage/mathseconomy/__init__.py
economypackage/mathseconomy/mathsadvancefunction.py
economypackage/mathseconomy/mymathsUtils.py
economypackage/utilseconomy/__init__.py
economypackage/utilseconomy/myeconomyutils.py
pypipackageexamplesbs-0.1.4.dist-info/licenses/LICENSE
pypipackageexamplesbs-0.1.4.dist-info/METADATA
pypipackageexamplesbs-0.1.4.dist-info/WHEEL
pypipackageexamplesbs-0.1.4.dist-info/top_level.txt
pypipackageexamplesbs-0.1.4.dist-info/RECORD
